{
  "$schema": "schema.json",
  "abilities": [],
  "faces": [],
  "replacements": [],
  "statics": [
    {
      "affected": {
        "card_type": "Card",
        "properties": [
          {
            "type": "EnchantedBy"
          }
        ],
        "type": "Typed"
      },
      "description": "You control enchanted creature.",
      "mode": "Continuous"
    }
  ],
  "triggers": [
    {
      "description": "When CARDNAME enters, untap enchanted creature.",
      "destination": "Battlefield",
      "mode": "ChangesZone",
      "origin": "Battlefield",
      "valid_card": {
        "type": "SelfRef"
      }
    },
    {
      "description": "When enchanted creature dies, return that card to the battlefield under its owner's control.",
      "destination": "Graveyard",
      "mode": "ChangesZone",
      "origin": "Battlefield",
      "valid_card": {
        "card_type": "Card",
        "properties": [
          {
            "type": "Other",
            "value": "AttachedBy"
          }
        ],
        "type": "Typed"
      }
    }
  ]
}
