{
  "$schema": "schema.json",
  "abilities": [],
  "faces": [],
  "replacements": [],
  "statics": [
    {
      "affected": {
        "card_type": "Creature",
        "properties": [
          {
            "type": "EnchantedBy"
          }
        ],
        "type": "Typed"
      },
      "description": "Enchanted creature gets +1/+1 for each Plains you control and has flying.",
      "mode": "Continuous",
      "modifications": [
        {
          "keyword": "Flying",
          "type": "AddKeyword"
        }
      ]
    }
  ],
  "triggers": []
}
