{
  "$schema": "schema.json",
  "abilities": [],
  "faces": [
    {
      "abilities": [
        {
          "cost": null,
          "description": "Whenever a creature enters this turn, you may draw a card.",
          "effect": {
            "type": "GenericEffect"
          },
          "kind": "Spell",
          "sub_ability": null
        }
      ],
      "replacements": [],
      "statics": [],
      "triggers": []
    },
    {
      "abilities": [
        {
          "cost": null,
          "description": "Create four 1/1 white Bird creature tokens with flying.",
          "effect": {
            "colors": [],
            "keywords": [],
            "name": "w_1_1_bird_flying",
            "power": 0,
            "toughness": 0,
            "type": "Token",
            "types": []
          },
          "kind": "Spell",
          "sub_ability": null
        }
      ],
      "replacements": [],
      "statics": [],
      "triggers": []
    }
  ],
  "replacements": [],
  "statics": [],
  "triggers": []
}
