{
  "$schema": "schema.json",
  "abilities": [
    {
      "kind": "Activated",
      "effect": {
        "type": "PutCounter",
        "counter_type": "P1P1",
        "count": 1,
        "target": {
          "type": "Filtered",
          "filter": "Creature.YouCtrl+Other"
        }
      },
      "cost": {
        "type": "Composite",
        "costs": [
          {
            "type": "Tap"
          },
          {
            "type": "Mana",
            "cost": "SubCounter<1/P1P1>"
          }
        ]
      },
      "sub_ability": null,
      "remaining_params": {
        "SpellDescription": "Put a +1/+1 counter on another target creature you control."
      }
    }
  ],
  "triggers": [],
  "statics": [],
  "replacements": [
    {
      "event": {
        "Other": "AddCounter"
      },
      "params": {
        "ValidCounterType": "P1P1",
        "ValidCard": "Creature.YouCtrl+inZoneBattlefield+Other",
        "ReplaceWith": "AddOneMoreCounters",
        "Description": "If one or more +1/+1 counters would be put on another creature you control, that many plus one +1/+1 counters are put on it instead.",
        "ActiveZones": "Battlefield"
      }
    }
  ],
  "faces": []
}
