{
  "$schema": "schema.json",
  "abilities": [],
  "faces": [],
  "replacements": [
    {
      "description": "Creatures with flying don't untap during their controllers' untap steps.",
      "event": {
        "Other": "Untap"
      },
      "valid_card": {
        "card_type": "Creature",
        "type": "Typed"
      }
    }
  ],
  "statics": [
    {
      "condition": {
        "filter": {
          "card_type": "Snow",
          "controller": "You",
          "properties": [
            {
              "type": "Other",
              "value": "Land"
            }
          ],
          "type": "Typed"
        },
        "type": "IsPresent"
      },
      "description": "Cast CARDNAME only if you control a snow land.",
      "effect_zone": "Battlefield",
      "mode": "CantBeCast"
    }
  ],
  "triggers": []
}
