{
  "$schema": "schema.json",
  "abilities": [],
  "triggers": [
    {
      "mode": "ChangesZone",
      "params": {
        "Origin": "Any",
        "Destination": "Battlefield",
        "Execute": "TrigDraw",
        "TriggerDescription": "When CARDNAME enters, draw three cards, then put two cards from your hand on top of your library in any order.",
        "ValidCard": "Card.Self"
      }
    },
    {
      "mode": "ChangesZone",
      "params": {
        "TriggerDescription": "When CARDNAME dies, shuffle it into its owner's library, then scry 2.",
        "Origin": "Battlefield",
        "Destination": "Graveyard",
        "ValidCard": "Card.Self",
        "Execute": "TrigChange"
      }
    }
  ],
  "statics": [],
  "replacements": [],
  "faces": []
}
