{
  "$schema": "schema.json",
  "abilities": [
    {
      "kind": "Activated",
      "effect": {
        "type": "Mana",
        "produced": "Combo W U",
        "params": {
          "SpellDescription": "Add {W} or {U}."
        }
      },
      "cost": {
        "type": "Tap"
      },
      "sub_ability": null,
      "remaining_params": {
        "SpellDescription": "Add {W} or {U}."
      }
    },
    {
      "kind": "Activated",
      "effect": {
        "type": "Animate",
        "power": 4,
        "toughness": 4,
        "types": [
          "Creature",
          "Elemental"
        ],
        "target": {
          "type": "Any"
        }
      },
      "cost": {
        "type": "Mana",
        "cost": "3 W U"
      },
      "sub_ability": null,
      "remaining_params": {
        "OverwriteColors": "True",
        "Colors": "White,Blue",
        "Defined": "Self",
        "SpellDescription": "Until end of turn, this land becomes a 4/4 white and blue Elemental creature with flying and vigilance. It's still a land.",
        "Keywords": "Flying & Vigilance"
      }
    }
  ],
  "triggers": [],
  "statics": [],
  "replacements": [
    {
      "event": "Moved",
      "params": {
        "ReplacementResult": "Updated",
        "Description": "This land enters tapped.",
        "Destination": "Battlefield",
        "ValidCard": "Card.Self",
        "ReplaceWith": "ETBTapped"
      }
    }
  ],
  "faces": []
}
