{
  "$schema": "schema.json",
  "abilities": [
    {
      "cost": null,
      "description": "CARDNAME deals 3 damage to target creature or planeswalker an opponent controls. CARDNAME deals 5 damage instead if you control a Chandra planeswalker.",
      "effect": {
        "amount": {
          "type": "Variable",
          "value": "X"
        },
        "target": {
          "card_type": "Creature",
          "properties": [
            {
              "type": "Other",
              "value": "OppCtrl,Planeswalker.OppCtrl"
            }
          ],
          "type": "Typed"
        },
        "type": "DealDamage"
      },
      "kind": "Spell",
      "sub_ability": null,
      "target_prompt": "Select target creature or planeswalker an opponent controls"
    }
  ],
  "faces": [],
  "replacements": [],
  "statics": [],
  "triggers": []
}
