{
  "$schema": "schema.json",
  "abilities": [],
  "triggers": [
    {
      "mode": "Phase",
      "params": {
        "Phase": "Upkeep",
        "ValidPlayer": "Player",
        "TriggerZones": "Battlefield",
        "Execute": "TrigGainLife",
        "TriggerDescription": "Domain — At the beginning of each player's upkeep, that player gains 1 life for each basic land type among lands they control. Then CARDNAME deals 3 damage to that player."
      }
    }
  ],
  "statics": [],
  "replacements": [],
  "faces": []
}
