{
  "$schema": "schema.json",
  "abilities": [
    {
      "cost": {
        "cost": "2 B",
        "type": "Mana"
      },
      "description": "Regenerate CARDNAME.",
      "effect": {
        "description": "Regenerate CARDNAME.",
        "name": "Regenerate",
        "type": "Unimplemented"
      },
      "kind": "Activated",
      "sub_ability": null
    }
  ],
  "faces": [],
  "replacements": [],
  "statics": [
    {
      "affected": {
        "type": "SelfRef"
      },
      "condition": {
        "filter": {
          "card_type": "Swamp",
          "controller": "You",
          "type": "Typed"
        },
        "type": "IsPresent"
      },
      "description": "CARDNAME gets +1/+1 as long as you control a Swamp.",
      "mode": "Continuous",
      "modifications": [
        {
          "type": "AddPower",
          "value": 1
        },
        {
          "type": "AddToughness",
          "value": 1
        }
      ]
    }
  ],
  "triggers": []
}
