{
  "$schema": "schema.json",
  "abilities": [],
  "triggers": [
    {
      "mode": "Phase",
      "params": {
        "TriggerZones": "Battlefield",
        "ValidPlayer": "You",
        "Execute": "TrigDestroy",
        "TriggerDescription": "At the beginning of your upkeep, destroy target nonland permanent with the lowest mana value. (If two or more permanents are tied for lowest, target any one of them.)",
        "Phase": "Upkeep"
      }
    }
  ],
  "statics": [],
  "replacements": [],
  "faces": []
}
