{
  "$schema": "schema.json",
  "abilities": [
    {
      "cost": {
        "type": "Tap"
      },
      "description": "Add {C}.",
      "effect": {
        "produced": [],
        "type": "Mana"
      },
      "kind": "Activated",
      "sub_ability": null
    },
    {
      "cost": {
        "costs": [
          {
            "cost": "2",
            "type": "Mana"
          },
          {
            "type": "Tap"
          },
          {
            "target": {
              "type": "None"
            },
            "type": "Sacrifice"
          }
        ],
        "type": "Composite"
      },
      "description": "Destroy target nonbasic land an opponent controls. That land's controller may search their library for a basic land card, put it onto the battlefield, then shuffle. You may search your library for a basic land card, put it onto the battlefield, then shuffle.",
      "effect": {
        "target": {
          "card_type": "Land",
          "controller": "Opponent",
          "type": "Typed"
        },
        "type": "Destroy"
      },
      "kind": "Activated",
      "sub_ability": null,
      "target_prompt": "Select target nonbasic land an opponent controls"
    }
  ],
  "faces": [],
  "replacements": [],
  "statics": [],
  "triggers": []
}
