{
  "$schema": "schema.json",
  "abilities": [],
  "faces": [],
  "replacements": [],
  "statics": [
    {
      "affected": {
        "filters": [
          {
            "card_type": "Creature",
            "controller": "You",
            "properties": [
              {
                "type": "Other",
                "value": "Zombie"
              }
            ],
            "type": "Typed"
          },
          {
            "filter": {
              "type": "SelfRef"
            },
            "type": "Not"
          }
        ],
        "type": "And"
      },
      "description": "Other Zombie creatures you control get +1/+1.",
      "mode": "Continuous",
      "modifications": [
        {
          "type": "AddPower",
          "value": 1
        },
        {
          "type": "AddToughness",
          "value": 1
        }
      ]
    }
  ],
  "triggers": [
    {
      "description": "Whenever another Zombie you control dies, target opponent loses 1 life.",
      "destination": "Graveyard",
      "mode": "ChangesZone",
      "origin": "Battlefield",
      "trigger_zones": [
        "Battlefield"
      ],
      "valid_card": {
        "filters": [
          {
            "controller": "You",
            "subtype": "Zombie",
            "type": "Typed"
          },
          {
            "filter": {
              "type": "SelfRef"
            },
            "type": "Not"
          }
        ],
        "type": "And"
      }
    }
  ]
}
