{
  "$schema": "schema.json",
  "abilities": [],
  "triggers": [
    {
      "mode": "ChangesZone",
      "params": {
        "Execute": "TrigChange",
        "Origin": "Any",
        "TriggerDescription": "When CARDNAME enters, return a blue or black creature you control to its owner's hand.",
        "ValidCard": "Card.Self",
        "Destination": "Battlefield"
      }
    },
    {
      "mode": "DamageDone",
      "params": {
        "TriggerZones": "Battlefield",
        "TriggerDescription": "Whenever CARDNAME deals combat damage to a player, look at that player's hand and choose a card from it. The player discards that card.",
        "Execute": "TrigDiscard",
        "ValidSource": "Card.Self",
        "ValidTarget": "Player",
        "CombatDamage": "True"
      }
    }
  ],
  "statics": [],
  "replacements": [],
  "faces": []
}
