{
  "$schema": "schema.json",
  "abilities": [],
  "triggers": [
    {
      "mode": "ChangesZoneAll",
      "params": {
        "ValidCards": "Artifact.YouOwn,Creature.YouOwn",
        "Origin": "Graveyard",
        "TriggerDescription": "Whenever one or more artifact and/or creature cards leave your graveyard, you gain 1 life.",
        "TriggerZones": "Battlefield",
        "Destination": "Any",
        "Execute": "TrigGainLife"
      }
    },
    {
      "mode": "ChangesZone",
      "params": {
        "TriggerDescription": "When this enchantment enters, mill four cards. You may put an artifact, creature, or land card from among the milled cards into your hand. (To mill four cards, put the top four cards of your library into your graveyard.)",
        "Destination": "Battlefield",
        "Execute": "TrigMill",
        "Origin": "Any",
        "ValidCard": "Card.Self"
      }
    }
  ],
  "statics": [],
  "replacements": [],
  "faces": []
}
