{
  "$schema": "schema.json",
  "abilities": [],
  "faces": [],
  "replacements": [],
  "statics": [
    {
      "affected": {
        "card_type": "Creature",
        "properties": [
          {
            "type": "EnchantedBy"
          }
        ],
        "type": "Typed"
      },
      "description": "Enchanted creature has \"{R}, {T}: Copy target instant or sorcery spell you control. You may choose new targets for the copy.\"",
      "mode": "Continuous",
      "modifications": [
        {
          "ability": "ForkStick",
          "type": "AddAbility"
        }
      ]
    }
  ],
  "triggers": []
}
