{
  "$schema": "schema.json",
  "abilities": [
    {
      "kind": "Activated",
      "effect": {
        "type": "Pump",
        "power": 0,
        "toughness": 0,
        "target": {
          "type": "Filtered",
          "filter": "Creature.Dwarf"
        }
      },
      "cost": {
        "type": "Composite",
        "costs": [
          {
            "type": "Mana",
            "cost": "1 R"
          },
          {
            "type": "Tap"
          }
        ]
      },
      "sub_ability": null,
      "remaining_params": {
        "SpellDescription": "Target Dwarf creature gains mountainwalk until end of turn. (It can't be blocked as long as defending player controls a Mountain.)",
        "TgtPrompt": "Select target Dwarf creature",
        "KW": "Landwalk:Mountain"
      }
    }
  ],
  "triggers": [],
  "statics": [],
  "replacements": [],
  "faces": []
}
