{
  "$schema": "schema.json",
  "abilities": [],
  "triggers": [
    {
      "mode": "Sacrificed",
      "params": {
        "TriggerZones": "Battlefield",
        "TriggerDescription": "Whenever one or more players sacrifice one or more creatures, you create a tapped Treasure token. This ability triggers only once each turn.",
        "ValidCard": "Creature",
        "ActivationLimit": "1",
        "Execute": "TrigTreasure"
      }
    }
  ],
  "statics": [
    {
      "mode": "Continuous",
      "params": {
        "AddPower": "X",
        "Description": "CARDNAME gets +2/+0 for each Treasure you control.",
        "Affected": "Card.Self"
      }
    }
  ],
  "replacements": [],
  "faces": []
}
