{
  "$schema": "schema.json",
  "abilities": [
    {
      "cost": null,
      "description": "Each player hides at least one item, then all players reveal them simultaneously. Each player loses life equal to the number of items they revealed. The player who revealed the fewest items then loses half their life, rounded up. If two or more players are tied for fewest, each loses half their life, rounded up.",
      "effect": {
        "description": "Each player hides at least one item, then all players reveal them simultaneously. Each player loses life equal to the number of items they revealed. The player who revealed the fewest items then loses half their life, rounded up. If two or more players are tied for fewest, each loses half their life, rounded up.",
        "name": "ChooseNumber",
        "type": "Unimplemented"
      },
      "kind": "Spell",
      "sub_ability": null
    }
  ],
  "faces": [],
  "replacements": [],
  "statics": [],
  "triggers": []
}
