{
  "$schema": "schema.json",
  "abilities": [
    {
      "cost": {
        "costs": [
          {
            "cost": "R",
            "type": "Mana"
          },
          {
            "target": {
              "type": "None"
            },
            "type": "Sacrifice"
          }
        ],
        "type": "Composite"
      },
      "description": "It deals damage equal to its power to target creature or planeswalker.",
      "effect": {
        "amount": {
          "type": "Variable",
          "value": "X"
        },
        "target": {
          "card_type": "Creature,Planeswalker",
          "type": "Typed"
        },
        "type": "DealDamage"
      },
      "kind": "Activated",
      "sub_ability": null,
      "target_prompt": "Select target creature or planeswalker"
    }
  ],
  "faces": [],
  "replacements": [],
  "statics": [],
  "triggers": []
}
