{
  "$schema": "schema.json",
  "abilities": [],
  "triggers": [
    {
      "mode": "ChangesZoneAll",
      "params": {
        "Origin": "Battlefield",
        "ValidCards": "Creature.!token+YouCtrl",
        "TriggerZones": "Battlefield",
        "Destination": "Graveyard",
        "TriggerDescription": "Whenever one or more nontoken creatures you control die, investigate. This ability triggers only once each turn. (Create a Clue token. It's an artifact with \"{2}, Sacrifice this artifact: Draw a card.\")",
        "Execute": "TrigInvestigate",
        "ActivationLimit": "1"
      }
    }
  ],
  "statics": [],
  "replacements": [],
  "faces": []
}
