{
  "$schema": "schema.json",
  "abilities": [
    {
      "kind": "Spell",
      "effect": {
        "type": "Destroy",
        "target": {
          "type": "Filtered",
          "filter": "Creature"
        }
      },
      "cost": {
        "type": "Composite",
        "costs": [
          {
            "type": "Mana",
            "cost": "2 B"
          },
          {
            "type": "Mana",
            "cost": "AddCounter<1/M1M1/Creature.YouCtrl/a creature you control>"
          }
        ]
      },
      "sub_ability": null,
      "remaining_params": {
        "SpellDescription": "Destroy target creature."
      }
    }
  ],
  "triggers": [],
  "statics": [],
  "replacements": [],
  "faces": []
}
