{
  "$schema": "schema.json",
  "abilities": [],
  "faces": [],
  "replacements": [],
  "statics": [
    {
      "affected": {
        "card_type": "Creature",
        "properties": [
          {
            "type": "Other",
            "value": "PairedWith,Creature.Self"
          },
          {
            "type": "Other",
            "value": "Paired"
          }
        ],
        "type": "Typed"
      },
      "description": "As long as CARDNAME is paired with another creature, each of those creatures has \"At the beginning of combat on your turn, create a token that's a copy of this creature, except it has haste and loses soulbond. Exile it at end of combat.\"",
      "mode": "Continuous"
    }
  ],
  "triggers": []
}
