{
  "$schema": "schema.json",
  "abilities": [],
  "faces": [],
  "replacements": [],
  "statics": [],
  "triggers": [
    {
      "description": "When CARDNAME enters, target creature gains menace and gets +X/+0 until end of turn, where X is the number of creature cards in your graveyard. (It can't blocked except by two or more creatures.)",
      "destination": "Battlefield",
      "mode": "ChangesZone",
      "origin": "Battlefield",
      "valid_card": {
        "type": "SelfRef"
      }
    }
  ]
}
