{
  "$schema": "schema.json",
  "abilities": [],
  "faces": [],
  "replacements": [
    {
      "description": "As long as you have a full party, prevent all damage that would be dealt to equipped creature.",
      "event": "DamageDone"
    }
  ],
  "statics": [
    {
      "affected": {
        "card_type": "Creature",
        "properties": [
          {
            "type": "EquippedBy"
          }
        ],
        "type": "Typed"
      },
      "condition": {
        "filter": {
          "card_type": "Cleric",
          "controller": "You",
          "type": "Typed"
        },
        "type": "IsPresent"
      },
      "description": "Equipped creature has lifelink if you control a Cleric, deathtouch if you control a Rogue, haste if you control a Warrior, and flying if you control a Wizard.",
      "mode": "Continuous",
      "modifications": [
        {
          "keyword": "Lifelink",
          "type": "AddKeyword"
        }
      ]
    },
    {
      "affected": {
        "card_type": "Creature",
        "properties": [
          {
            "type": "EquippedBy"
          }
        ],
        "type": "Typed"
      },
      "condition": {
        "filter": {
          "card_type": "Rogue",
          "controller": "You",
          "type": "Typed"
        },
        "type": "IsPresent"
      },
      "mode": "Continuous",
      "modifications": [
        {
          "keyword": "Deathtouch",
          "type": "AddKeyword"
        }
      ]
    },
    {
      "affected": {
        "card_type": "Creature",
        "properties": [
          {
            "type": "EquippedBy"
          }
        ],
        "type": "Typed"
      },
      "condition": {
        "filter": {
          "card_type": "Warrior",
          "controller": "You",
          "type": "Typed"
        },
        "type": "IsPresent"
      },
      "mode": "Continuous",
      "modifications": [
        {
          "keyword": "Haste",
          "type": "AddKeyword"
        }
      ]
    },
    {
      "affected": {
        "card_type": "Creature",
        "properties": [
          {
            "type": "EquippedBy"
          }
        ],
        "type": "Typed"
      },
      "condition": {
        "filter": {
          "card_type": "Wizard",
          "controller": "You",
          "type": "Typed"
        },
        "type": "IsPresent"
      },
      "mode": "Continuous",
      "modifications": [
        {
          "keyword": "Flying",
          "type": "AddKeyword"
        }
      ]
    }
  ],
  "triggers": []
}
