{
  "$schema": "schema.json",
  "abilities": [],
  "triggers": [
    {
      "mode": "ChangesZone",
      "params": {
        "TriggerDescription": "When NICKNAME enters, create X Mutagen tokens. (They're artifacts with \"{1}, {T}, Sacrifice this token: Put a +1/+1 counter on target creature. Activate only as a sorcery.\")",
        "Origin": "Any",
        "Destination": "Battlefield",
        "ValidCard": "Card.Self",
        "Execute": "TrigToken"
      }
    }
  ],
  "statics": [
    {
      "mode": "ReduceCost",
      "params": {
        "Description": "Activated abilities of artifact tokens you control cost {1} less to activate.",
        "Type": "Ability",
        "Amount": "1",
        "ValidCard": "Artifact.token+YouCtrl",
        "AffectedZone": "Battlefield"
      }
    }
  ],
  "replacements": [],
  "faces": []
}
