{
  "$schema": "schema.json",
  "abilities": [],
  "faces": [],
  "replacements": [],
  "statics": [
    {
      "affected": {
        "card_type": "Card",
        "properties": [
          {
            "type": "Other",
            "value": "IsCommander"
          },
          {
            "type": "Other",
            "value": "YouOwn"
          }
        ],
        "type": "Typed"
      },
      "description": "Your commander has ward {2}.",
      "effect_zone": "Command",
      "mode": "Continuous",
      "modifications": [
        {
          "keyword": "Ward:2",
          "type": "AddKeyword"
        }
      ]
    }
  ],
  "triggers": [
    {
      "description": "Whenever your commander attacks, put two +1/+1 counters on it.",
      "mode": "Attacks",
      "trigger_zones": [
        "Command"
      ],
      "valid_card": {
        "card_type": "Card",
        "properties": [
          {
            "type": "Other",
            "value": "IsCommander"
          },
          {
            "type": "Other",
            "value": "YouOwn"
          }
        ],
        "type": "Typed"
      }
    },
    {
      "description": "When your commander leaves the battlefield, abandon this scheme.",
      "destination": "Graveyard",
      "mode": "ChangesZone",
      "origin": "Battlefield",
      "trigger_zones": [
        "Command"
      ],
      "valid_card": {
        "card_type": "Card",
        "properties": [
          {
            "type": "Other",
            "value": "IsCommander"
          },
          {
            "type": "Other",
            "value": "YouOwn"
          }
        ],
        "type": "Typed"
      }
    }
  ]
}
