{
  "$schema": "schema.json",
  "abilities": [],
  "faces": [],
  "replacements": [],
  "statics": [
    {
      "affected": {
        "card_type": "Land",
        "type": "Typed"
      },
      "description": "All lands are 2/2 creatures that are still lands.",
      "mode": "Continuous",
      "modifications": [
        {
          "type": "SetPower",
          "value": 2
        },
        {
          "type": "SetToughness",
          "value": 2
        },
        {
          "core_type": "Creature",
          "type": "AddType"
        }
      ]
    }
  ],
  "triggers": []
}
