{
  "$schema": "schema.json",
  "abilities": [
    {
      "kind": "Activated",
      "effect": {
        "type": "ChangeZone",
        "origin": "Library",
        "destination": "Battlefield",
        "target": {
          "type": "Any"
        }
      },
      "cost": {
        "type": "Loyalty",
        "amount": 1
      },
      "sub_ability": null,
      "remaining_params": {
        "Planeswalker": "True",
        "SpellDescription": "Search your library for a card named Nissa's Chosen, put it onto the battlefield, then shuffle.",
        "StackDescription": "SpellDescription",
        "ChangeNum": "1",
        "ChangeType": "Permanent.namedNissa's Chosen"
      }
    },
    {
      "kind": "Activated",
      "effect": {
        "type": "GainLife",
        "amount": 0
      },
      "cost": {
        "type": "Loyalty",
        "amount": 1
      },
      "sub_ability": null,
      "remaining_params": {
        "SpellDescription": "You gain 2 life for each Elf you control.",
        "Planeswalker": "True"
      }
    },
    {
      "kind": "Activated",
      "effect": {
        "type": "ChangeZone",
        "origin": "Library",
        "destination": "Battlefield",
        "target": {
          "type": "Any"
        }
      },
      "cost": {
        "type": "Loyalty",
        "amount": -7
      },
      "sub_ability": null,
      "remaining_params": {
        "Planeswalker": "True",
        "Ultimate": "True",
        "ChangeType": "Creature.Elf",
        "ChangeNum": "XFetch",
        "StackDescription": "SpellDescription",
        "SpellDescription": "Search your library for any number of Elf creature cards, put them onto the battlefield, then shuffle."
      }
    }
  ],
  "triggers": [],
  "statics": [],
  "replacements": [],
  "faces": []
}
