{
  "$schema": "schema.json",
  "abilities": [
    {
      "cost": {
        "type": "Tap"
      },
      "description": "Target opponent chooses any number of creatures they control. During that player's next turn, the chosen creatures attack if able, and other creatures can't attack. At the beginning of that turn's end step, destroy each of the chosen creatures that didn't attack this turn. Activate only during your turn.",
      "effect": {
        "choices": [
          "Creature"
        ],
        "target": {
          "type": "Player"
        },
        "type": "ChooseCard"
      },
      "kind": "Activated",
      "sub_ability": null
    }
  ],
  "faces": [],
  "replacements": [],
  "statics": [],
  "triggers": []
}
