{
  "$schema": "schema.json",
  "abilities": [],
  "faces": [],
  "replacements": [],
  "statics": [
    {
      "description": "CARDNAME can't be blocked by creatures with power 2 or less.",
      "mode": {
        "Other": "CantBlockBy"
      }
    }
  ],
  "triggers": [
    {
      "description": "Whenever CARDNAME deals combat damage to a player or dies, proliferate.",
      "destination": "Graveyard",
      "mode": "ChangesZone",
      "origin": "Battlefield",
      "valid_card": {
        "type": "SelfRef"
      }
    },
    {
      "combat_damage": true,
      "description": "Whenever CARDNAME deals combat damage to a player or dies, proliferate.",
      "mode": "DamageDone",
      "secondary": true,
      "valid_source": {
        "type": "SelfRef"
      },
      "valid_target": {
        "type": "Player"
      }
    }
  ]
}
