{
  "$schema": "schema.json",
  "abilities": [
    {
      "kind": "Activated",
      "effect": {
        "type": "ChangeZone",
        "origin": "Graveyard",
        "destination": "Exile",
        "target": {
          "type": "Filtered",
          "filter": "Creature.YouOwn"
        }
      },
      "cost": {
        "type": "Mana",
        "cost": "2 U"
      },
      "sub_ability": null,
      "remaining_params": {
        "TgtPrompt": "Select target creature from your graveyard",
        "SubAbility": "DBCounter",
        "SpellDescription": "Exile target creature from your graveyard and put a +1/+1 counter on CARDNAME."
      }
    }
  ],
  "triggers": [],
  "statics": [
    {
      "mode": "Continuous",
      "params": {
        "GainsAbilitiesOfZones": "Exile",
        "Description": "CARDNAME has all activated abilities of all creature cards exiled with it.",
        "EffectZone": "Battlefield",
        "GainsAbilitiesOf": "Creature.ExiledWithSource",
        "Affected": "Card.Self"
      }
    }
  ],
  "replacements": [],
  "faces": []
}
