{
  "$schema": "schema.json",
  "abilities": [
    {
      "cost": {
        "type": "Tap"
      },
      "description": "For as long as CARDNAME remains tapped, gain control of target creature of an opponent's choice they control.",
      "effect": {
        "target": {
          "card_type": "Creature",
          "type": "Typed"
        },
        "type": "GainControl"
      },
      "kind": "Activated",
      "sub_ability": null,
      "target_prompt": "Select target creature you control"
    }
  ],
  "faces": [],
  "replacements": [],
  "statics": [],
  "triggers": []
}
