{
  "$schema": "schema.json",
  "abilities": [],
  "faces": [],
  "replacements": [],
  "statics": [
    {
      "affected": {
        "filters": [
          {
            "card_type": "Permanent",
            "controller": "You",
            "type": "Typed"
          },
          {
            "filter": {
              "type": "SelfRef"
            },
            "type": "Not"
          }
        ],
        "type": "And"
      },
      "description": "Other permanents you control have hexproof. (They can't be the targets of spells or abilities your opponents control.)",
      "mode": "Continuous",
      "modifications": [
        {
          "keyword": "Hexproof",
          "type": "AddKeyword"
        }
      ]
    }
  ],
  "triggers": []
}
