{
  "$schema": "schema.json",
  "abilities": [
    {
      "cost": null,
      "description": "Shuffle your library, then mill four cards. Put each creature card milled this way onto the battlefield. They gain haste.",
      "effect": {
        "description": "Shuffle your library, then mill four cards. Put each creature card milled this way onto the battlefield. They gain haste.",
        "name": "Shuffle",
        "type": "Unimplemented"
      },
      "kind": "Spell",
      "sub_ability": null
    }
  ],
  "faces": [],
  "replacements": [],
  "statics": [],
  "triggers": []
}
