{
  "$schema": "schema.json",
  "abilities": [
    {
      "cost": {
        "type": "Tap"
      },
      "description": "Each player mills a card. (They each put the top card of their library in their graveyard.)",
      "effect": {
        "count": 1,
        "target": {
          "type": "Any"
        },
        "type": "Mill"
      },
      "kind": "Activated",
      "sub_ability": null
    }
  ],
  "faces": [],
  "replacements": [],
  "statics": [
    {
      "affected": {
        "card_type": "Card",
        "properties": [
          {
            "type": "NonType",
            "value": "Land"
          },
          {
            "type": "Other",
            "value": "YouOwn"
          }
        ],
        "type": "Typed"
      },
      "affected_zone": "Graveyard",
      "description": "Once during each of your turns, you may cast a spell from among cards in your graveyard that were milled this turn.",
      "mode": "Continuous"
    }
  ],
  "triggers": []
}
