{
  "$schema": "schema.json",
  "abilities": [
    {
      "cost": null,
      "description": "Copy target instant or sorcery spell. You may choose new targets for the copy.",
      "effect": {
        "description": "Copy target instant or sorcery spell. You may choose new targets for the copy.",
        "name": "CopySpellAbility",
        "type": "Unimplemented"
      },
      "kind": "Spell",
      "sub_ability": null
    }
  ],
  "faces": [],
  "replacements": [],
  "statics": [],
  "triggers": []
}
