{
  "$schema": "schema.json",
  "abilities": [],
  "faces": [],
  "replacements": [],
  "statics": [],
  "triggers": [
    {
      "description": "When CARDNAME enters, if the gift was promised, destroy target artifact or enchantment an opponent controls.",
      "destination": "Battlefield",
      "mode": "ChangesZone",
      "origin": "Battlefield",
      "valid_card": {
        "card_type": "Card",
        "properties": [
          {
            "type": "Other",
            "value": "Self"
          },
          {
            "type": "Other",
            "value": "PromisedGift"
          }
        ],
        "type": "Typed"
      }
    }
  ]
}
