{
  "$schema": "schema.json",
  "abilities": [
    {
      "kind": "Spell",
      "effect": {
        "type": "Pump",
        "power": 0,
        "toughness": 0,
        "target": {
          "type": "Filtered",
          "filter": "Creature"
        }
      },
      "cost": null,
      "sub_ability": null,
      "remaining_params": {
        "IsCurse": "True",
        "SpellDescription": "Prevent all damage one or two target creatures would deal this turn.",
        "TargetMax": "2",
        "TargetMin": "1",
        "KW": "Prevent all damage that would be dealt by CARDNAME."
      }
    }
  ],
  "triggers": [],
  "statics": [],
  "replacements": [],
  "faces": []
}
