{
  "$schema": "schema.json",
  "abilities": [
    {
      "cost": {
        "costs": [
          {
            "cost": "6",
            "type": "Mana"
          },
          {
            "cost": "ExileFromGrave<1/CARDNAME>",
            "type": "Mana"
          }
        ],
        "type": "Composite"
      },
      "description": "Create two tapped 1/1 colorless Robot artifact creature tokens with flying.",
      "effect": {
        "colors": [],
        "keywords": [],
        "name": "c_1_1_a_robot_flying",
        "power": 0,
        "toughness": 0,
        "type": "Token",
        "types": []
      },
      "kind": "Activated",
      "sub_ability": null
    }
  ],
  "faces": [],
  "replacements": [],
  "statics": [],
  "triggers": [
    {
      "description": "Whenever NICKNAME deals damage to a Spider, destroy that creature.",
      "mode": "DamageDone",
      "trigger_zones": [
        "Battlefield"
      ],
      "valid_source": {
        "type": "SelfRef"
      },
      "valid_target": {
        "card_type": "Spider",
        "type": "Typed"
      }
    }
  ]
}
