{
  "$schema": "schema.json",
  "abilities": [
    {
      "cost": null,
      "description": "Until end of turn, target creature you control gains indestructible and \"Whenever this creature is dealt damage, put that many +1/+1 counters on it.\"",
      "effect": {
        "power": null,
        "target": {
          "card_type": "Creature",
          "controller": "You",
          "type": "Typed"
        },
        "toughness": null,
        "type": "Animate",
        "types": []
      },
      "kind": "Spell",
      "sub_ability": null,
      "target_prompt": "Select target creature you control"
    }
  ],
  "faces": [],
  "replacements": [],
  "statics": [],
  "triggers": []
}
