{
  "$schema": "schema.json",
  "abilities": [
    {
      "cost": {
        "type": "Tap"
      },
      "description": "Add {W}.",
      "effect": {
        "produced": [
          "White"
        ],
        "type": "Mana"
      },
      "kind": "Activated",
      "sub_ability": null
    },
    {
      "cost": {
        "type": "Tap"
      },
      "description": "Add {R}. Activate only if you control a Mountain or a Plains.",
      "effect": {
        "produced": [
          "Red"
        ],
        "type": "Mana"
      },
      "kind": "Activated",
      "sub_ability": null
    }
  ],
  "faces": [],
  "replacements": [],
  "statics": [],
  "triggers": []
}
