{
  "$schema": "schema.json",
  "abilities": [
    {
      "cost": {
        "costs": [
          {
            "cost": {
              "Cost": {
                "generic": 1,
                "shards": [
                  "White"
                ]
              }
            },
            "type": "Mana"
          },
          {
            "type": "Tap"
          }
        ],
        "type": "Composite"
      },
      "description": "Tap target creature with power 4 or greater.",
      "effect": {
        "target": {
          "card_type": "Creature",
          "type": "Typed"
        },
        "type": "Tap"
      },
      "kind": "Activated",
      "sub_ability": null,
      "target_prompt": "Select target creature with power 4 or greater"
    },
    {
      "cost": {
        "costs": [
          {
            "cost": {
              "Cost": {
                "generic": 4,
                "shards": [
                  "Black"
                ]
              }
            },
            "type": "Mana"
          },
          {
            "type": "Tap"
          }
        ],
        "type": "Composite"
      },
      "description": "CARDNAME deals 2 damage to target opponent or planeswalker.",
      "effect": {
        "amount": {
          "type": "Fixed",
          "value": 2
        },
        "target": {
          "card_type": "Planeswalker",
          "type": "Typed"
        },
        "type": "DealDamage"
      },
      "kind": "Activated",
      "sub_ability": null,
      "target_prompt": "Select target opponent or planeswalker"
    }
  ],
  "faces": [],
  "replacements": [],
  "statics": [],
  "triggers": []
}
