{
  "$schema": "schema.json",
  "abilities": [
    {
      "cost": {
        "amount": 2,
        "type": "Loyalty"
      },
      "description": "Untap up to one target artifact or creature.",
      "effect": {
        "target": {
          "card_type": "Artifact,Creature",
          "type": "Typed"
        },
        "type": "Untap"
      },
      "kind": "Activated",
      "sub_ability": null,
      "target_prompt": "Choose target artifact or creature"
    },
    {
      "cost": {
        "amount": -3,
        "type": "Loyalty"
      },
      "description": "You gain 2 life and draw two cards.",
      "effect": {
        "amount": 2,
        "type": "GainLife"
      },
      "kind": "Activated",
      "sub_ability": null
    },
    {
      "cost": {
        "amount": -9,
        "type": "Loyalty"
      },
      "description": "Take an extra turn after this one.",
      "effect": {
        "description": "Take an extra turn after this one.",
        "name": "AddTurn",
        "type": "Unimplemented"
      },
      "kind": "Activated",
      "sub_ability": null
    }
  ],
  "faces": [],
  "replacements": [],
  "statics": [],
  "triggers": []
}
