{
  "$schema": "schema.json",
  "abilities": [
    {
      "cost": {
        "costs": [
          {
            "cost": "2 B",
            "type": "Mana"
          },
          {
            "target": {
              "type": "None"
            },
            "type": "Sacrifice"
          }
        ],
        "type": "Composite"
      },
      "description": "Target player discards a number of cards equal to the sacrificed creature's power.",
      "effect": {
        "count": 1,
        "target": {
          "type": "Player"
        },
        "type": "Discard"
      },
      "kind": "Spell",
      "sub_ability": null
    }
  ],
  "faces": [],
  "replacements": [],
  "statics": [],
  "triggers": []
}
