{
  "$schema": "schema.json",
  "abilities": [
    {
      "kind": "Spell",
      "effect": {
        "type": "GenericEffect",
        "params": {
          "AILogic": "Fog",
          "ReplacementEffects": "RPrevent",
          "SpellDescription": "Prevent all combat damage that would be dealt this turn by creatures with power 4 or less."
        }
      },
      "cost": null,
      "sub_ability": null,
      "remaining_params": {
        "AILogic": "Fog",
        "ReplacementEffects": "RPrevent",
        "SpellDescription": "Prevent all combat damage that would be dealt this turn by creatures with power 4 or less."
      }
    }
  ],
  "triggers": [],
  "statics": [],
  "replacements": [],
  "faces": []
}
