{
  "$schema": "schema.json",
  "abilities": [
    {
      "kind": "Activated",
      "effect": {
        "type": "Other",
        "api_type": "Reveal",
        "params": {
          "RememberRevealed": "True",
          "PlayerTurn": "True",
          "ValidTgts": "Player",
          "SubAbility": "DBDiscard1",
          "IsCurse": "True",
          "SpellDescription": "Target player reveals a card at random from their hand. If it's a land card, that player discards it unless they pay 1 life. If it isn't a land card, the player discards it unless they pay life equal to its mana value. Activate only during your turn.",
          "Random": "True"
        }
      },
      "cost": {
        "type": "Composite",
        "costs": [
          {
            "type": "Mana",
            "cost": "3"
          },
          {
            "type": "Tap"
          }
        ]
      },
      "sub_ability": null,
      "remaining_params": {
        "RememberRevealed": "True",
        "PlayerTurn": "True",
        "ValidTgts": "Player",
        "SubAbility": "DBDiscard1",
        "IsCurse": "True",
        "SpellDescription": "Target player reveals a card at random from their hand. If it's a land card, that player discards it unless they pay 1 life. If it isn't a land card, the player discards it unless they pay life equal to its mana value. Activate only during your turn.",
        "Random": "True"
      }
    }
  ],
  "triggers": [],
  "statics": [],
  "replacements": [],
  "faces": []
}
